paralleldelaunay/__init__.py
paralleldelaunay/triangulation_core/__init__.py
paralleldelaunay/triangulation_core/edge_topology.py
paralleldelaunay/triangulation_core/linear_algebra.py
paralleldelaunay/triangulation_core/points_tools/__init__.py
paralleldelaunay/triangulation_core/points_tools/generate_values.py
paralleldelaunay/triangulation_core/points_tools/split_list.py
paralleldelaunay/triangulation_core/triangulation.py
paralleldelaunay/triangulation_core/triangulation_primitives.py
paralleldelaunay/utilities/__init__.py
paralleldelaunay/utilities/settings.py
parallel_delaunay-1.0.0.dist-info/LICENSE
parallel_delaunay-1.0.0.dist-info/METADATA
parallel_delaunay-1.0.0.dist-info/WHEEL
parallel_delaunay-1.0.0.dist-info/RECORD
