Metadata-Version: 2.1
Name: parallel-delaunay
Version: 1.0.0
Summary: Parallel implementation of Guibas & Stolfi's divide-and-conquer algorithm for Delaunay triangulation, using MPI in Python.
Home-page: https://github.com/v-hill/parallel-delaunay
License: MIT
Author: v-hill
Author-email: 67915924+v-hill@users.noreply.github.com
Requires-Python: >=3.8,<3.12
Classifier: License :: OSI Approved :: MIT License
Classifier: Programming Language :: Python :: 3
Classifier: Programming Language :: Python :: 3.8
Classifier: Programming Language :: Python :: 3.9
Classifier: Programming Language :: Python :: 3.10
Classifier: Programming Language :: Python :: 3.11
Requires-Dist: matplotlib (>=3.6.2,<4.0.0)
Requires-Dist: mpi4py (>=3.1.4,<4.0.0)
Requires-Dist: numpy (>=1.23.5,<2.0.0)
Requires-Dist: scipy (>=1.10.0,<2.0.0)
Project-URL: Repository, https://github.com/v-hill/parallel-delaunay
